README.txt
setup.cfg
setup.py
collective/__init__.py
collective.tagcloud.egg-info/PKG-INFO
collective.tagcloud.egg-info/SOURCES.txt
collective.tagcloud.egg-info/dependency_links.txt
collective.tagcloud.egg-info/entry_points.txt
collective.tagcloud.egg-info/namespace_packages.txt
collective.tagcloud.egg-info/not-zip-safe
collective.tagcloud.egg-info/paster_plugins.txt
collective.tagcloud.egg-info/pkg-info
collective.tagcloud.egg-info/requires.txt
collective.tagcloud.egg-info/top_level.txt
collective/tagcloud/__init__.py
collective/tagcloud/configure.zcml
collective/tagcloud/interfaces.py
collective/tagcloud/portlet.pt
collective/tagcloud/portlet.pt.bak
collective/tagcloud/portlet.py
collective/tagcloud/tests.py
collective/tagcloud/viewlet.pt
collective/tagcloud/viewlet.py
collective/tagcloud/browser/__init__.py
collective/tagcloud/browser/configure.zcml
collective/tagcloud/browser/tagcloud.css
collective/tagcloud/browser/tagcloud.pt
collective/tagcloud/browser/tagcloud.py
collective/tagcloud/profiles/default/cssregistry.xml
collective/tagcloud/profiles/default/metadata.xml
collective/tagcloud/profiles/default/portlets.xml
collective/tagcloud/profiles/default/viewlets.xml
docs/HISTORY.txt
docs/INSTALL.txt
docs/LICENSE.txt
docs/license.gpl