Metadata-Version: 1.0
Name: collective.tagcloud
Version: 0.1
Summary: a tag cloud for Plone
Home-page: http://svn.plone.org/svn/plone/plone.example
Author: Luis Miguel Braga
Author-email: lmb@eurotux.com
License: GPL
Keywords: tag cloud subject
Platform: UNKNOWN
Classifier: Framework :: Plone
Classifier: Programming Language :: Python
Classifier: Topic :: Software Development :: Libraries :: Python Modules
